pzp/__init__.py
pzp/actions.py
pzp/ansi.py
pzp/candidates.py
pzp/commons.py
pzp/config.py
pzp/exceptions.py
pzp/finder.py
pzp/info.py
pzp/input.py
pzp/input_posix.py
pzp/input_win.py
pzp/keys.py
pzp/layout.py
pzp/line_editor.py
pzp/matcher.py
pzp/prompt.py
pzp/py.typed
pzp/screen.py
pzp-0.0.27.dist-info/LICENSE
pzp-0.0.27.dist-info/METADATA
pzp-0.0.27.dist-info/WHEEL
pzp-0.0.27.dist-info/top_level.txt
pzp-0.0.27.dist-info/zip-safe
pzp-0.0.27.dist-info/RECORD
