Metadata-Version: 2.2
Name: pzp
Version: 0.0.27
Summary: Pure-python fzf-inspired element picker
Home-page: http://github.com/andreax79/pzp
Author: Andrea Bonomi
Author-email: andrea.bonomi@gmail.com
License: MIT
Project-URL: Bug Tracker, http://github.com/andreax79/pzp/issues
Project-URL: Documentation, https://pzp.readthedocs.io/en/latest/
Project-URL: Source Code, http://github.com/andreax79/pzp
Keywords: fzf,picker,cli
Platform: any
Classifier: Development Status :: 5 - Production/Stable
Classifier: Environment :: Console
Classifier: Intended Audience :: Developers
Classifier: License :: OSI Approved :: MIT License
Classifier: Operating System :: OS Independent
Classifier: Programming Language :: Python
Classifier: Topic :: Software Development :: Libraries :: Python Modules
Classifier: Programming Language :: Python :: 3.6
Classifier: Programming Language :: Python :: 3.7
Classifier: Programming Language :: Python :: 3.8
Classifier: Programming Language :: Python :: 3.9
Classifier: Programming Language :: Python :: 3.10
Classifier: Programming Language :: Python :: 3.11
Classifier: Programming Language :: Python :: 3.12
Classifier: Programming Language :: Python :: 3.13
Requires-Python: >=3.6
License-File: LICENSE
Provides-Extra: test
Requires-Dist: pytest; extra == "test"
